quantium/__init__.py
quantium/core/dimensions.py
quantium/core/quantity.py
quantium/core/utils.py
quantium/units/__init__.py
quantium/units/parser.py
quantium/units/prefixes.py
quantium/units/registry.py
quantium-0.1.0.dist-info/licenses/LICENSE
quantium-0.1.0.dist-info/METADATA
quantium-0.1.0.dist-info/WHEEL
quantium-0.1.0.dist-info/top_level.txt
quantium-0.1.0.dist-info/RECORD
