Metadata-Version: 2.4
Name: quantium
Version: 0.1.0
Summary: A modern Python library for dimensional analysis and unit-safe scientific computation.
Author: Parneet Sidhu
License: MIT
Keywords: Python,open-source,physics,numpy,unit-conversion,dimensional-analysis,units,scientific-computing,quantium
Requires-Python: >=3.10
License-File: LICENSE
Requires-Dist: typing-extensions
Dynamic: license-file
